aligndg/__init__.py
aligndg/graph/AlignDG.py
aligndg/graph/__init__.py
aligndg/graph/layer.py
aligndg/graph/model.py
aligndg/uopt/__init__.py
aligndg/uopt/_constants.py
aligndg/uopt/_logging.py
aligndg/uopt/_registry.py
aligndg/uopt/_types.py
aligndg/uopt/datasets.py
aligndg/uopt/backends/__init__.py
aligndg/uopt/backends/utils.py
aligndg/uopt/backends/ott/__init__.py
aligndg/uopt/backends/ott/_utils.py
aligndg/uopt/backends/ott/output.py
aligndg/uopt/backends/ott/solver.py
aligndg/uopt/base/__init__.py
aligndg/uopt/base/cost.py
aligndg/uopt/base/output.py
aligndg/uopt/base/solver.py
aligndg/uopt/base/problems/__init__.py
aligndg/uopt/base/problems/_mixins.py
aligndg/uopt/base/problems/_utils.py
aligndg/uopt/base/problems/birth_death.py
aligndg/uopt/base/problems/compound_problem.py
aligndg/uopt/base/problems/manager.py
aligndg/uopt/base/problems/problem.py
aligndg/uopt/costs/__init__.py
aligndg/uopt/costs/_costs.py
aligndg/uopt/costs/_utils.py
aligndg/uopt/plotting/__init__.py
aligndg/uopt/plotting/_plotting.py
aligndg/uopt/plotting/_utils.py
aligndg/uopt/problems/__init__.py
aligndg/uopt/problems/_utils.py
aligndg/uopt/problems/space/__init__.py
aligndg/uopt/problems/space/_alignment.py
aligndg/uopt/problems/space/_mapping.py
aligndg/uopt/problems/space/_mixins.py
aligndg/uopt/utils/__init__.py
aligndg/uopt/utils/data.py
aligndg/uopt/utils/subset_policy.py
aligndg/uopt/utils/tagged_array.py
aligndg/utils/color.py
aligndg/utils/graph_construction.py
aligndg/utils/icp.py
aligndg/utils/metrics.py
aligndg/utils/model.py
aligndg/utils/multi_dataset.py
aligndg/utils/prematch.py
aligndg/utils/seed.py
aligndg/utils/visualize.py
aligndg-1.0.2.dist-info/licenses/LICENSE
aligndg-1.0.2.dist-info/METADATA
aligndg-1.0.2.dist-info/WHEEL
aligndg-1.0.2.dist-info/top_level.txt
aligndg-1.0.2.dist-info/RECORD
