Metadata-Version: 2.4
Name: aligndg
Version: 1.0.2
Summary: The initial package of AlignDG
Home-page: https://github.com/xkmaxidian/AlignDG
Author: Yu Wang
Author-email: Yu Wang <yuwangxdu@163.com>
Project-URL: Homepage, https://github.com/xkmaxidian/AlignDG
Project-URL: Issues, https://github.com/xkmaxidian/AlignDG/issues
Classifier: Programming Language :: Python :: 3
Classifier: License :: OSI Approved :: MIT License
Classifier: Operating System :: OS Independent
Requires-Python: >=3.10
License-File: LICENSE
Requires-Dist: scanpy>=1.9.3
Requires-Dist: numpy>=1.24.0
Requires-Dist: pandas
Requires-Dist: anndata>=0.9.0
Requires-Dist: matplotlib>=3.5.0
Requires-Dist: scipy>=1.11.2
Requires-Dist: scikit-learn>=1.2.2
Requires-Dist: psutil>=5.9.0
Requires-Dist: cloudpickle>=2.2.0
Requires-Dist: tqdm>=4.65.0
Requires-Dist: leidenalg>=0.10.1
Requires-Dist: networkx>=3.2.0
Requires-Dist: docrep>=0.3.2
Requires-Dist: jax>=0.6.0
Requires-Dist: ott-jax[neural]>=0.5.0
Requires-Dist: torch>=2.0.1
Requires-Dist: torch-geometric>=2.3.1
Requires-Dist: wrapt>=1.13.2
Requires-Dist: rich>=13.5.0
Requires-Dist: plotly
Requires-Dist: pyyaml
Requires-Dist: torch-geometric
Requires-Dist: torch-cluster
Requires-Dist: torch-scatter
Requires-Dist: torch-sparse
Dynamic: author
Dynamic: home-page
Dynamic: license-file
